LICENSE
MANIFEST.in
README.md
setup.py
tests/__init__.py
tests/http_response_catcher.py
tests/test_helper.py
tests/controllers/__init__.py
tests/controllers/controller_test_base.py
tests/controllers/test_api_controller.py
xrqwpgfaey/__init__.py
xrqwpgfaey/api_helper.py
xrqwpgfaey/configuration.py
xrqwpgfaey/decorators.py
xrqwpgfaey/xrqwpgfaey_client.py
xrqwpgfaey.egg-info/PKG-INFO
xrqwpgfaey.egg-info/SOURCES.txt
xrqwpgfaey.egg-info/dependency_links.txt
xrqwpgfaey.egg-info/requires.txt
xrqwpgfaey.egg-info/top_level.txt
xrqwpgfaey/controllers/__init__.py
xrqwpgfaey/controllers/api_controller.py
xrqwpgfaey/controllers/base_controller.py
xrqwpgfaey/exceptions/__init__.py
xrqwpgfaey/exceptions/api_exception.py
xrqwpgfaey/http/__init__.py
xrqwpgfaey/http/http_call_back.py
xrqwpgfaey/http/http_client.py
xrqwpgfaey/http/http_context.py
xrqwpgfaey/http/http_method_enum.py
xrqwpgfaey/http/http_request.py
xrqwpgfaey/http/http_response.py
xrqwpgfaey/http/requests_client.py
xrqwpgfaey/http/auth/__init__.py
xrqwpgfaey/http/auth/basic_auth.py
xrqwpgfaey/models/__init__.py
xrqwpgfaey/models/suite_code_enum.py